Workbook

Sheet Inicio
B2: AUTOEVALUACIÓN DE ARQUITECTURA LEGAL DE CIBERSEGURIDAD
B3: Arquetipo legislativo mínimo viable · América Latina y el Caribe · 10 pilares / 59 subpilares / 177 ítems
B5: CÓMO LLENARLO (3 pasos)
B6: 1. Abra la hoja «Autoevaluación». Cada subpilar tiene 3 ítems. En la columna amarilla «Nivel (0-4)»
B7: elija un número de 0 a 4 (hay menú desplegable al hacer clic en la celda). Esa es la ÚNICA columna obligatoria.
B8: 2. Opcional: anote en «Evidencia» el artículo de su ley y en «Nota» qué falta para subir de nivel.
B9: 3. Las hojas «Resumen» y «Tablero» se calculan solas: promedian los ítems por subpilar y por pilar.
B11: SI LA GRÁFICA O LOS NÚMEROS NO CAMBIAN
B12: • Use Excel de escritorio o LibreOffice. En Google Sheets el radar puede importarse como imagen fija;
B13: las celdas de color de las hojas «Resumen» y «Tablero» sí se actualizan en cualquier programa.
B14: • Si nada recalcula: menú Fórmulas → Opciones de cálculo → Automático (o pulse F9 / Cmd + =).
B15: • El radar promedia muchos ítems: cambiar un solo ítem lo mueve poco. Mire mejor la hoja «Resumen».
... B24: • Las referencias (NIS2, DORA, CRA, CER, CSA, Chile 21.663…) son anclas de redacción, no de copia literal.

Sheet Escala
A1: RÚBRICA DE MADUREZ (0-4)
A3: Nivel | B3: Etiqueta | C3: Descripción
A4: 0 | B4: Ausente | C4: No hay base normativa identificable para el elemento.
A5: 1 | B5: Disperso / implícito | C5: Existe solo en normas penales, sectoriales o administrativas fragmentadas (brecha conceptual).
A6: 2 | B6: Previsto no habilitante | C6: Mencionado, pero sin lex specialis, sin competencias ni estándares verificables (brecha normativa).
A7: 3 | B7: Establecido en ley especial | C7: Definido en ley, con autoridad y deberes exigibles (arquitectura legal cubierta).
A8: 4 | B8: Establecido y verificable | C8: Además con métricas/KPIs, plazos y trazabilidad operativa (cierre de la brecha operativa).
A10: Lectura: nivel ≥ 3 = ya está en una ley especial (cobertura legal). Nivel 4 = además operativo y verificable.

Sheet Autoevaluación
A1: Pilar | B1: Ref | C1: Subpilar | D1: Tier | E1: Ítem a verificar | F1: Nivel (0-4) | G1: Evidencia (art./sección de su ley) | H1: Nota / acción
A2: A | B2: A1 | C2: Definiciones | D2: Núcleo | E2: • Define los términos núcleo (incidente, riesgo, vulnerabilidad, entidad obligada) de forma cerrada. | F2: 0
B3: A1 | E3: • Alinea la terminología con estándares y con otras leyes (penal, datos, sectorial), sin contradicciones. | F3: 0
B4: A1 | E4: • No esconde obligaciones materiales dentro de las definiciones (un término, un significado). | F4: 0
A5: A | B5: A2 | C5: Ámbito y extraterritorialidad | D5: Núcleo | E5: • Delimita el alcance material, subjetivo y sectorial (qué sí y qué no). | F5: 0
B6: A2 | E6: • Usa impacto sistémico/criticidad como criterio (no solo tamaño) y prevé exclusiones e interfaces. | F6: 0
B7: A2 | E7: • Regula la extraterritorialidad funcional (aplica si el servicio afecta al país). | F7: 0
A8: A | B8: A3 | C8: Autoridad / Agencia nacional | D8: Núcleo | E8: • Crea la autoridad con mandato legal expreso y función rectora/coordinadora. | F8: 0
B9: A3 | E9: • Le otorga potestad normativa secundaria, de información, supervisión y sanción. | F9: 0
B10: A3 | E10: • Le asegura presupuesto, personal y autonomía técnica; separa asistencia de sanción. | F10: 0
A11: A | B11: A4 | C11: Estrategia, políticas, planes y KPIs | D11: Núcleo | E11: • Exige estrategia nacional con objetivos, responsables y secuencia de implementación. | F11: 0
B12: A4 | E12: • Incluye indicadores (KPIs) y mecanismos de revisión periódica. | F12: 0
B13: A4 | E13: • Distingue la estrategia (ex ante) de las potestades/sanciones de la ley. | F13: 0
A14: A | B14: A5 | C14: Roles institucionales | D14: Núcleo | E14: • Asigna accountability a la alta dirección u órgano de gobierno. | F14: 0
B15: A5 | E15: • Crea gestión especializada (CISO/delegado) distinta del jefe de TI. | F15: 0
B16: A5 | E16: • Define coordinación/respuesta (SPOC, CSIRT) y canales de reporte vertical y horizontal. | F16: 0
A17: A | B17: A6 | C17: Consejo multiactor | D17: Intermedio | E17: • Institucionaliza un consejo consultivo permanente y plural (no consulta esporádica). | F17: 0
B18: A6 | E18: • Define su función como consultiva (asesora, no decide). | F18: 0
B19: A6 | E19: • Fija reglas de integridad, abstención y reserva. | F19: 0
A20: A | B20: A7 | C20: Transparencia y derechos | D20: Núcleo | E20: • Fija salvaguardas de derechos como límite (legalidad, necesidad, proporcionalidad). | F20: 0
B21: A7 | E21: • Protege el cifrado de extremo a extremo frente a debilitamientos estructurales. | F21: 0
B22: A7 | E22: • Incluye una cláusula de no-retroceso (no degradar garantías ya reconocidas). | F22: 0
A23: A | B23: A8 | C23: Métricas y rendición de cuentas | D23: Intermedio | E23: • Obliga a medir estrategia y capacidades con métricas ordinarias. | F23: 0
B24: A8 | E24: • Prevé evaluación institucional independiente o entre pares. | F24: 0
B25: A8 | E25: • Institucionaliza la revisión post-incidente (aprendizaje). | F25: 0
A26: A | B26: A9 | C26: Ventanilla única (one-stop) | D26: Intermedio | E26: • Establece un punto único de contacto (one-stop). | F26: 0
B27: A9 | E27: • Fija reglas anti-duplicidad: el regulado reporta una vez y el Estado redistribuye. | F27: 0
B28: A9 | E28: • Armoniza contenidos/plantillas de reporte entre autoridades. | F28: 0
A29: A | B29: A10 | C29: VEP (0-days) | D29: Avanzado | E29: • Crea un proceso estatal trazable para ponderar retención/divulgación de 0-days. | F29: 0
B30: A10 | E30: • Lo asigna a una instancia colegiada con secretaría y registro documental. | F30: 0
B31: A10 | E31: • Impone reevaluación periódica (no retención indefinida) e informe. | F31: 0
A32: B | B32: B1 | C32: CSIRT / CERT nacionales o sectoriales | D32: Núcleo | E32: • Designa formalmente uno o más CSIRT y define su constituency. | F32: 0
B33: B1 | E33: • Fija mandato mínimo, disponibilidad continua y canales seguros. | F33: 0
B34: B1 | E34: • Asegura recursos/continuidad y reglas de coordinación nacional e internacional. | F34: 0
A35: B | B35: B2 | C35: Gestión de crisis y continuidad | D35: Núcleo | E35: • Designa autoridad/comité de gestión de crisis de gran escala. | F35: 0
B36: B2 | E36: • Exige un plan nacional de respuesta con roles, umbrales y escalamiento. | F36: 0
B37: B2 | E37: • Ordena ejercicios periódicos, protocolos de comunicación y continuidad de funciones críticas. | F37: 0
A38: B | B38: B3 | C38: CTI y compartición | D38: Intermedio | E38: • Habilita el intercambio voluntario/estructurado de CTI (IoC, TTPs, near misses). | F38: 0
B39: B3 | E39: • Otorga safe harbor frente a responsabilidad por compartir de buena fe. | F39: 0
B40: B3 | E40: • Resuelve la tensión de competencia/antimonopolio para que la información circule. | F40: 0
A41: B | B41: B4 | C41: GovSOC / Centro Nacional | D41: Avanzado | E41: • Crea capacidad de monitoreo continuo del sector público (GovSOC). | F41: 0
B42: B4 | E42: • Habilita correlación de telemetría y producción de alertas/conciencia situacional. | F42: 0
B43: B4 | E43: • Establece enlace técnico directo con el CSIRT e interoperabilidad con estructuras de alerta. | F43: 0
A44: B | B44: B5 | C44: Respuesta comunicacional | D44: Intermedio | E44: • Define avisos a los afectados y al público cuando proceda. | F44: 0
B45: B5 | E45: • Coordina mensajes entre autoridades técnicas, regulatorias y de crisis (portavoz/roles). | F45: 0
B46: B5 | E46: • Prevé auxilio/solidaridad de emergencia y documentación de resultados. | F46: 0
A47: C | B47: C1 | C47: ISMS / SGSI | D47: Núcleo | E47: • Exige medidas técnicas/organizativas apropiadas y proporcionales (enfoque all-hazards). | F47: 0
B48: C1 | E48: • Cubre el ciclo política → riesgo → controles → monitoreo → mejora (sistema, no checklist). | F48: 0
B49: C1 | E49: • Remite a estándares (ISO 27001/27002) como referente, sin imponer certificación cerrada. | F49: 0
A50: C | B50: C2 | C50: Cadena de suministro / MSP / MSSP | D50: Núcleo | E50: • Obliga a gestionar el riesgo de proveedores directos y MSP/MSSP. | F50: 0
B51: C2 | E51: • Considera vulnerabilidades y calidad de prácticas del proveedor en la selección. | F51: 0
B52: C2 | E52: • Habilita trazabilidad de componentes (SBOM) y mejores contratos. | F52: 0
A53: C | B53: C3 | C53: Nube / servicios gestionados | D53: Intermedio | E53: • Asegura control operativo real (logs, telemetría, portabilidad), no solo localización. | F53: 0
B54: C3 | E54: • Aclara que externalizar infraestructura no externaliza la responsabilidad. | F54: 0
B55: C3 | E55: • Aborda la soberanía operativa sin convertirla en proteccionismo encubierto. | F55: 0
A56: C | B56: C4 | C56: Awareness y formación por rol | D56: Intermedio | E56: • Impone ciberhigiene básica como piso común. | F56: 0
B57: C4 | E57: • Exige formación periódica proporcional al rol, incluida la alta dirección. | F57: 0
B58: C4 | E58: • Alcanza a terceros/proveedores en funciones críticas, con gobernanza y presupuesto. | F58: 0
A59: C | B59: C5 | C59: Divulgación responsable / buena fe | D59: Intermedio | E59: • Exige una política de divulgación (VDP) con alcance, reglas y punto de contacto. | F59: 0
B60: C5 | E60: • Estructura recepción, análisis, remediación y respuesta al reportante (CVD). | F60: 0
B61: C5 | E61: • Reconoce safe harbor para investigación de buena fe y delimita pruebas autorizadas. | F61: 0
A62: D | B62: D1 | C62: Sectores / operadores esenciales | D62: Núcleo | E62: • Define el criterio de entrada (qué sectores/servicios entran por ley). | F62: 0
B63: D1 | E63: • Permite intensificación/designación administrativa por criticidad. | F63: 0
B64: D1 | E64: • Mantiene un registro/lista nacional con revisión periódica. | F64: 0
A65: D | B65: D2 | C65: Obligaciones reforzadas | D65: Intermedio | E65: • Impone obligaciones avanzadas escalables y proporcionales al riesgo sistémico. | F65: 0
B66: D2 | E66: • Exige continuidad con metas (RTO/RPO) y validación, no solo políticas escritas. | F66: 0
B67: D2 | E67: • Habilita pruebas avanzadas (tipo TLPT) para los operadores más sensibles. | F67: 0
A68: D | B68: D3 | C68: Supervisión sectorial y coordinación | D68: Núcleo | E68: • Designa autoridad(es) competente(s) y un punto único de contacto. | F68: 0
B69: D3 | E69: • Fija reglas expresas de reparto competencial (rectoría + sectoriales equivalentes). | F69: 0
B70: D3 | E70: • Establece coordinación previa anti-duplicidad/solapamiento. | F70: 0
A71: D | B71: D4 | C71: Interdependencias / cascada | D71: Avanzado | E71: • Exige evaluación nacional de interdependencias intersectoriales. | F71: 0
B72: D4 | E72: • Obliga a cada entidad crítica a evaluar sus dependencias mutuas. | F72: 0
B73: D4 | E73: • Habilita pruebas conjuntas y revisión de incidentes sistémicos (efecto cascada). | F73: 0
A74: D | B74: D5 | C74: OT / ICS (físico-lógico) | D74: Avanzado | E74: • Da tratamiento específico a OT/ICS cuando hay proceso físico-digital relevante. | F74: 0
B75: D5 | E75: • Remite a un marco técnico reconocido (p. ej. ISA/IEC 62443) sin absorber su detalle. | F75: 0
B76: D5 | E76: • Distribuye responsabilidades por roles (asset owner, integrador, proveedor) y habilita auditoría. | F76: 0
A77: E | B77: E1 | C77: Umbrales y plazos | D77: Núcleo | E77: • Fija un umbral de significancia que dispara el deber de reportar. | F77: 0
B78: E1 | E78: • Establece reporte escalonado por fases con plazos (p. ej. 24 h / 72 h / final). | F78: 0
B79: E1 | E79: • Define el canal/autoridad receptora y la trazabilidad del expediente. | F79: 0
A80: E | B80: E2 | C80: Contenido del reporte | D80: Núcleo | E80: • Define el contenido por fases (alerta temprana / notificación / informe final). | F80: 0
B81: E2 | E81: • Asegura información suficiente para triage y correlación (IoC, TTPs). | F81: 0
B82: E2 | E82: • Permite que la autoridad/CSIRT cierre el bucle con acuse, feedback y orientación. | F82: 0
A83: E | B83: E3 | C83: Ransomware | D83: Avanzado | E83: • Distingue el ransomware (cifrado, exfiltración, amenaza de publicación) del incidente genérico. | F83: 0
B84: E3 | E84: • Crea reporte específico del pago con plazo perentorio y conexión al expediente. | F84: 0
B85: E3 | E85: • Activa coordinación con sanciones y con AML/CFT cuando proceda. | F85: 0
A86: E | B86: E4 | C86: Protección del informante / víctima | D86: Núcleo | E86: • La mera notificación no agrava la responsabilidad ni es admisión de culpa. | F86: 0
B87: E4 | E87: • Protege la confidencialidad del informante de buena fe frente a represalias. | F87: 0
B88: E4 | E88: • Permite reportes voluntarios y de near misses por canal seguro. | F88: 0
A89: E | B89: E5 | C89: Clasificación de severidad | D89: Intermedio | E89: • Define criterios comunes de severidad (no a discreción del reportante). | F89: 0
B90: E5 | E90: • Los vincula con variables objetivas y verificables. | F90: 0
B91: E5 | E91: • Conecta severidad con disparadores de reporte y escalamiento; deja margen sectorial. | F91: 0
A92: E | B92: E6 | C92: Lecciones aprendidas / post-mortem | D92: Intermedio | E92: • Obliga a revisión posterior interna (causa raíz, eficacia de respuesta) supervisable. | F92: 0
B93: E6 | E93: • Verifica si procedimientos, escalamiento y comunicación funcionaron. | F93: 0
B94: E6 | E94: • Prevé aprendizaje sistémico para incidentes significativos o transfronterizos. | F94: 0
A95: E | B95: E7 | C95: Interoperabilidad de reportes | D95: Avanzado | E95: • Define formularios, campos obligatorios, glosarios y validaciones. | F95: 0
B96: E7 | E96: • Exige canales seguros y circuito de respuesta/actualización (sin pedir lo mismo dos veces). | F96: 0
B97: E7 | E97: • Habilita interoperabilidad técnica avanzada (STIX 2.1/TAXII 2.1) entre autoridades/CSIRTs. | F97: 0
A98: F | B98: F1 | C98: Productos / IoT | D98: Intermedio | E98: • Impone diseño seguro, evaluación de riesgo y período de soporte comunicable. | F98: 0
B99: F1 | E99: • Exige manejo de vulnerabilidades/CVD con punto de contacto durante el soporte. | F99: 0
B100: F1 | E100: • Regula el fin de soporte (EoL) visible y extiende la lógica a IoT/radio. | F100: 0
...

Sheet Resumen
A1: Pilar | B1: Ref | C1: Subpilar | D1: Tier | E1: Nivel subpilar | F1: Etiqueta | G1: ¿En ley? (≥3) | H1: Prioridad
A2: A | B2: A1 | C2: Definiciones | D2: Núcleo | E2: =IFERROR(AVERAGEIF(Autoevaluación!$B$2:$B$178,B2,Autoevaluación!$F$2:$F$178),0) -> 0 | F2: =IFERROR(VLOOKUP(ROUND(E2,0),Escala!$A$4:$B$8,2,FALSE()),"") -> Ausente | G2: =IF(E2>=3,"Sí","No") -> No | H2: =IF(E2>=3,"En ley",IF(D2="Núcleo","ALTA",IF(D2="Intermedio","MEDIA","BAJA"))) -> ALTA
A3: A | B3: A2 | C3: Ámbito y extraterritorialidad | D3: Núcleo | E3: =IFERROR(AVERAGEIF(Autoevaluación!$B$2:$B$178,B3,Autoevaluación!$F$2:$F$178),0) -> 0 | F3: =IFERROR(VLOOKUP(ROUND(E3,0),Escala!$A$4:$B$8,2,FALSE()),"") -> Ausente | G3: =IF(E3>=3,"Sí","No") -> No | H3: =IF(E3>=3,"En ley",IF(D3="Núcleo","ALTA",IF(D3="Intermedio","MEDIA","BAJA"))) -> ALTA
A4: A | B4: A3 | C4: Autoridad / Agencia nacional | D4: Núcleo | E4: =IFERROR(AVERAGEIF(Autoevaluación!$B$2:$B$178,B4,Autoevaluación!$F$2:$F$178),0) -> 0 | F4: =IFERROR(VLOOKUP(ROUND(E4,0),Escala!$A$4:$B$8,2,FALSE()),"") -> Ausente | G4: =IF(E4>=3,"Sí","No") -> No | H4: =IF(E4>=3,"En ley",IF(D4="Núcleo","ALTA",IF(D4="Intermedio","MEDIA","BAJA"))) -> ALTA
A5: A | B5: A4 | C5: Estrategia, políticas, planes y KPIs | D5: Núcleo | E5: =IFERROR(AVERAGEIF(Autoevaluación!$B$2:$B$178,B5,Autoevaluación!$F$2:$F$178),0) -> 0 | F5: =IFERROR(VLOOKUP(ROUND(E5,0),Escala!$A$4:$B$8,2,FALSE()),"") -> Ausente | G5: =IF(E5>=3,"Sí","No") -> No | H5: =IF(E5>=3,"En ley",IF(D5="Núcleo","ALTA",IF(D5="Intermedio","MEDIA","BAJA"))) -> ALTA
A6: A | B6: A5 | C6: Roles institucionales | D6: Núcleo | E6: =IFERROR(AVERAGEIF(Autoevaluación!$B$2:$B$178,B6,Autoevaluación!$F$2:$F$178),0) -> 0 | F6: =IFERROR(VLOOKUP(ROUND(E6,0),Escala!$A$4:$B$8,2,FALSE()),"") -> Ausente | G6: =IF(E6>=3,"Sí","No") -> No | H6: =IF(E6>=3,"En ley",IF(D6="Núcleo","ALTA",IF(D6="Intermedio","MEDIA","BAJA"))) -> ALTA
A7: A | B7: A6 | C7: Consejo multiactor | D7: Intermedio | E7: =IFERROR(AVERAGEIF(Autoevaluación!$B$2:$B$178,B7,Autoevaluación!$F$2:$F$178),0) -> 0 | F7: =IFERROR(VLOOKUP(ROUND(E7,0),Escala!$A$4:$B$8,2,FALSE()),"") -> Ausente | G7: =IF(E7>=3,"Sí","No") -> No | H7: =IF(E7>=3,"En ley",IF(D7="Núcleo","ALTA",IF(D7="Intermedio","MEDIA","BAJA"))) -> MEDIA
A8: A | B8: A7 | C8: Transparencia y derechos | D8: Núcleo | E8: =IFERROR(AVERAGEIF(Autoevaluación!$B$2:$B$178,B8,Autoevaluación!$F$2:$F$178),0) -> 0 | F8: =IFERROR(VLOOKUP(ROUND(E8,0),Escala!$A$4:$B$8,2,FALSE()),"") -> Ausente | G8: =IF(E8>=3,"Sí","No") -> No | H8: =IF(E8>=3,"En ley",IF(D8="Núcleo","ALTA",IF(D8="Intermedio","MEDIA","BAJA"))) -> ALTA
A9: A | B9: A8 | C9: Métricas y rendición de cuentas | D9: Intermedio | E9: =IFERROR(AVERAGEIF(Autoevaluación!$B$2:$B$178,B9,Autoevaluación!$F$2:$F$178),0) -> 0 | F9: =IFERROR(VLOOKUP(ROUND(E9,0),Escala!$A$4:$B$8,2,FALSE()),"") -> Ausente | G9: =IF(E9>=3,"Sí","No") -> No | H9: =IF(E9>=3,"En ley",IF(D9="Núcleo","ALTA",IF(D9="Intermedio","MEDIA","BAJA"))) -> MEDIA
A10: A | B10: A9 | C10: Ventanilla única (one-stop) | D10: Intermedio | E10: =IFERROR(AVERAGEIF(Autoevaluación!$B$2:$B$178,B10,Autoevaluación!$F$2:$F$178),0) -> 0 | F10: =IFERROR(VLOOKUP(ROUND(E10,0),Escala!$A$4:$B$8,2,FALSE()),"") -> Ausente | G10: =IF(E10>=3,"Sí","No") -> No | H10: =IF(E10>=3,"En ley",IF(D10="Núcleo","ALTA",IF(D10="Intermedio","MEDIA","BAJA"))) -> MEDIA
A11: A | B11: A10 | C11: VEP (0-days) | D11: Avanzado | E11: =IFERROR(AVERAGEIF(Autoevaluación!$B$2:$B$178,B11,Autoevaluación!$F$2:$F$178),0) -> 0 | F11: =IFERROR(VLOOKUP(ROUND(E11,0),Escala!$A$4:$B$8,2,FALSE()),"") -> Ausente | G11: =IF(E11>=3,"Sí","No") -> No | H11: =IF(E11>=3,"En ley",IF(D11="Núcleo","ALTA",IF(D11="Intermedio","MEDIA","BAJA"))) -> BAJA
A12: B | B12: B1 | C12: CSIRT / CERT nacionales o sectoriales | D12: Núcleo | E12: =IFERROR(AVERAGEIF(Autoevaluación!$B$2:$B$178,B12,Autoevaluación!$F$2:$F$178),0) -> 0 | F12: =IFERROR(VLOOKUP(ROUND(E12,0),Escala!$A$4:$B$8,2,FALSE()),"") -> Ausente | G12: =IF(E12>=3,"Sí","No") -> No | H12: =IF(E12>=3,"En ley",IF(D12="Núcleo","ALTA",IF(D12="Intermedio","MEDIA","BAJA"))) -> ALTA
A13: B | B13: B2 | C13: Gestión de crisis y continuidad | D13: Núcleo | E13: =IFERROR(AVERAGEIF(Autoevaluación!$B$2:$B$178,B13,Autoevaluación!$F$2:$F$178),0) -> 0 | F13: =IFERROR(VLOOKUP(ROUND(E13,0),Escala!$A$4:$B$8,2,FALSE()),"") -> Ausente | G13: =IF(E13>=3,"Sí","No") -> No | H13: =IF(E13>=3,"En ley",IF(D13="Núcleo","ALTA",IF(D13="Intermedio","MEDIA","BAJA"))) -> ALTA
... A60: J | B60: J4 | C60: Publicidad proporcional | D60: Intermedio | E60: =IFERROR(AVERAGEIF(Autoevaluación!$B$2:$B$178,B60,Autoevaluación!$F$2:$F$178),0) -> 0 | F60: =IFERROR(VLOOKUP(ROUND(E60,0),Escala!$A$4:$B$8,2,FALSE()),"") -> Ausente | G60: =IF(E60>=3,"Sí","No") -> No | H60: =IF(E60>=3,"En ley",IF(D60="Núcleo","ALTA",IF(D60="Intermedio","MEDIA","BAJA"))) -> MEDIA

Sheet Tablero
B2: TABLERO DE RESULTADOS
B3: Se recalcula al cambiar la columna «Nivel» de la hoja Autoevaluación.
B5: Nivel promedio (0-4) | C5: Cobertura legal (≥3) | D5: Madurez operativa (=4) | E5: Brechas Núcleo abiertas
B6: =IFERROR(AVERAGE(Resumen!$E$2:$E$60),0) -> 0 | C6: =COUNTIF(Resumen!$E$2:$E$60,">=3")/59 -> 0 | D6: =COUNTIF(Resumen!$E$2:$E$60,"=4")/59 -> 0 | E6: =COUNTIFS(Resumen!$D$2:$D$60,"Núcleo",Resumen!$E$2:$E$60,"<3") -> 19
B9: Pilar | C9: Nombre | D9: Subpilares | E9: Nivel prom. | F9: Cobertura ≥3 | G9: Madurez =4 | H9: Brechas Núcleo
B10: A | C10: Gobernanza y coordinación nacional | D10: =COUNTIF(Resumen!$A$2:$A$60,"A") -> 10 | E10: =IFERROR(AVERAGEIF(Resumen!$A$2:$A$60,"A",Resumen!$E$2:$E$60),0) -> 0 | F10: =COUNTIFS(Resumen!$A$2:$A$60,"A",Resumen!$E$2:$E$60,">=3")/COUNTIF(Resumen!$A$2:$A$60,"A") -> 0 | G10: =COUNTIFS(Resumen!$A$2:$A$60,"A",Resumen!$E$2:$E$60,"=4")/COUNTIF(Resumen!$A$2:$A$60,"A") -> 0 | H10: =COUNTIFS(Resumen!$A$2:$A$60,"A",Resumen!$D$2:$D$60,"Núcleo",Resumen!$E$2:$E$60,"<3") -> 6
B11: B | C11: Capacidades operativas del Estado | D11: =COUNTIF(Resumen!$A$2:$A$60,"B") -> 5 | E11: =IFERROR(AVERAGEIF(Resumen!$A$2:$A$60,"B",Resumen!$E$2:$E$60),0) -> 0 | F11: =COUNTIFS(Resumen!$A$2:$A$60,"B",Resumen!$E$2:$E$60,">=3")/COUNTIF(Resumen!$A$2:$A$60,"B") -> 0 | G11: =COUNTIFS(Resumen!$A$2:$A$60,"B",Resumen!$E$2:$E$60,"=4")/COUNTIF(Resumen!$A$2:$A$60,"B") -> 0 | H11: =COUNTIFS(Resumen!$A$2:$A$60,"B",Resumen!$D$2:$D$60,"Núcleo",Resumen!$E$2:$E$60,"<3") -> 2
B12: C | C12: Gestión de riesgos e higiene digital | D12: =COUNTIF(Resumen!$A$2:$A$60,"C") -> 5 | E12: =IFERROR(AVERAGEIF(Resumen!$A$2:$A$60,"C",Resumen!$E$2:$E$60),0) -> 0 | F12: =COUNTIFS(Resumen!$A$2:$A$60,"C",Resumen!$E$2:$E$60,">=3")/COUNTIF(Resumen!$A$2:$A$60,"C") -> 0 | G12: =COUNTIFS(Resumen!$A$2:$A$60,"C",Resumen!$E$2:$E$60,"=4")/COUNTIF(Resumen!$A$2:$A$60,"C") -> 0 | H12: =COUNTIFS(Resumen!$A$2:$A$60,"C",Resumen!$D$2:$D$60,"Núcleo",Resumen!$E$2:$E$60,"<3") -> 2
B13: D | C13: Infraestructuras esenciales / sectores críticos | D13: =COUNTIF(Resumen!$A$2:$A$60,"D") -> 5 | E13: =IFERROR(AVERAGEIF(Resumen!$A$2:$A$60,"D",Resumen!$E$2:$E$60),0) -> 0 | F13: =COUNTIFS(Resumen!$A$2:$A$60,"D",Resumen!$E$2:$E$60,">=3")/COUNTIF(Resumen!$A$2:$A$60,"D") -> 0 | G13: =COUNTIFS(Resumen!$A$2:$A$60,"D",Resumen!$E$2:$E$60,"=4")/COUNTIF(Resumen!$A$2:$A$60,"D") -> 0 | H13: =COUNTIFS(Resumen!$A$2:$A$60,"D",Resumen!$D$2:$D$60,"Núcleo",Resumen!$E$2:$E$60,"<3") -> 2
B14: E | C14: Reportes y gestión de incidentes | D14: =COUNTIF(Resumen!$A$2:$A$60,"E") -> 7 | E14: =IFERROR(AVERAGEIF(Resumen!$A$2:$A$60,"E",Resumen!$E$2:$E$60),0) -> 0 | F14: =COUNTIFS(Resumen!$A$2:$A$60,"E",Resumen!$E$2:$E$60,">=3")/COUNTIF(Resumen!$A$2:$A$60,"E") -> 0 | G14: =COUNTIFS(Resumen!$A$2:$A$60,"E",Resumen!$E$2:$E$60,"=4")/COUNTIF(Resumen!$A$2:$A$60,"E") -> 0 | H14: =COUNTIFS(Resumen!$A$2:$A$60,"E",Resumen!$D$2:$D$60,"Núcleo",Resumen!$E$2:$E$60,"<3") -> 3
B15: F | C15: Seguridad de productos, servicios y certificación | D15: =COUNTIF(Resumen!$A$2:$A$60,"F") -> 6 | E15: =IFERROR(AVERAGEIF(Resumen!$A$2:$A$60,"F",Resumen!$E$2:$E$60),0) -> 0 | F15: =COUNTIFS(Resumen!$A$2:$A$60,"F",Resumen!$E$2:$E$60,">=3")/COUNTIF(Resumen!$A$2:$A$60,"F") -> 0 | G15: =COUNTIFS(Resumen!$A$2:$A$60,"F",Resumen!$E$2:$E$60,"=4")/COUNTIF(Resumen!$A$2:$A$60,"F") -> 0 | H15: =COUNTIFS(Resumen!$A$2:$A$60,"F",Resumen!$D$2:$D$60,"Núcleo",Resumen!$E$2:$E$60,"<3") -> 0
B16: G | C16: Cooperación internacional y ciberdiplomacia | D16: =COUNTIF(Resumen!$A$2:$A$60,"G") -> 7 | E16: =IFERROR(AVERAGEIF(Resumen!$A$2:$A$60,"G",Resumen!$E$2:$E$60),0) -> 0 | F16: =COUNTIFS(Resumen!$A$2:$A$60,"G",Resumen!$E$2:$E$60,">=3")/COUNTIF(Resumen!$A$2:$A$60,"G") -> 0 | G16: =COUNTIFS(Resumen!$A$2:$A$60,"G",Resumen!$E$2:$E$60,"=4")/COUNTIF(Resumen!$A$2:$A$60,"G") -> 0 | H16: =COUNTIFS(Resumen!$A$2:$A$60,"G",Resumen!$D$2:$D$60,"Núcleo",Resumen!$E$2:$E$60,"<3") -> 0
B17: H | C17: Gobierno, compras públicas y fomento | D17: =COUNTIF(Resumen!$A$2:$A$60,"H") -> 6 | E17: =IFERROR(AVERAGEIF(Resumen!$A$2:$A$60,"H",Resumen!$E$2:$E$60),0) -> 0 | F17: =COUNTIFS(Resumen!$A$2:$A$60,"H",Resumen!$E$2:$E$60,">=3")/COUNTIF(Resumen!$A$2:$A$60,"H") -> 0 | G17: =COUNTIFS(Resumen!$A$2:$A$60,"H",Resumen!$E$2:$E$60,"=4")/COUNTIF(Resumen!$A$2:$A$60,"H") -> 0 | H17: =COUNTIFS(Resumen!$A$2:$A$60,"H",Resumen!$D$2:$D$60,"Núcleo",Resumen!$E$2:$E$60,"<3") -> 0
B18: I | C18: Transparencia, presupuesto y sostenibilidad | D18: =COUNTIF(Resumen!$A$2:$A$60,"I") -> 4 | E18: =IFERROR(AVERAGEIF(Resumen!$A$2:$A$60,"I",Resumen!$E$2:$E$60),0) -> 0 | F18: =COUNTIFS(Resumen!$A$2:$A$60,"I",Resumen!$E$2:$E$60,">=3")/COUNTIF(Resumen!$A$2:$A$60,"I") -> 0 | G18: =COUNTIFS(Resumen!$A$2:$A$60,"I",Resumen!$E$2:$E$60,"=4")/COUNTIF(Resumen!$A$2:$A$60,"I") -> 0 | H18: =COUNTIFS(Resumen!$A$2:$A$60,"I",Resumen!$D$2:$D$60,"Núcleo",Resumen!$E$2:$E$60,"<3") -> 2
B19: J | C19: Responsabilidades y sanciones | D19: =COUNTIF(Resumen!$A$2:$A$60,"J") -> 4 | E19: =IFERROR(AVERAGEIF(Resumen!$A$2:$A$60,"J",Resumen!$E$2:$E$60),0) -> 0 | F19: =COUNTIFS(Resumen!$A$2:$A$60,"J",Resumen!$E$2:$E$60,">=3")/COUNTIF(Resumen!$A$2:$A$60,"J") -> 0 | G19: =COUNTIFS(Resumen!$A$2:$A$60,"J",Resumen!$E$2:$E$60,"=4")/COUNTIF(Resumen!$A$2:$A$60,"J") -> 0 | H19: =COUNTIFS(Resumen!$A$2:$A$60,"J",Resumen!$D$2:$D$60,"Núcleo",Resumen!$E$2:$E$60,"<3") -> 2
B20: TOTAL | D20: =SUM(D10:D19) -> 59 | E20: =IFERROR(AVERAGE(Resumen!$E$2:$E$60),0) -> 0 | F20: =COUNTIF(Resumen!$E$2:$E$60,">=3")/59 -> 0 | G20: =COUNTIF(Resumen!$E$2:$E$60,"=4")/59 -> 0 | H20: =COUNTIFS(Resumen!$D$2:$D$60,"Núcleo",Resumen!$E$2:$E$60,"<3") -> 19
B21: Radar (solo Excel/LibreOffice). Para feedback universal, mire los colores de «Nivel prom.» y de la hoja Resumen.
